{"otherData": {},"traceEvents":[{"cat":"function","dur":20,"name":"Gameplay update","ph":"X","pid":0,"tid":2846169341,"ts":51542316222},{"cat":"function","dur":10,"name":"Rendering - Prep","ph":"X","pid":0,"tid":2846169341,"ts":51542316583},{"cat":"function","dur":1558,"name":"Rendering - Draw","ph":"X","pid":0,"tid":2846169341,"ts":51542316675},{"cat":"function","dur":1,"name":"Rendering - Shutdown","ph":"X","pid":0,"tid":2846169341,"ts":51542318410},{"cat":"function","dur":2312,"name":"void __cdecl Shake::EditorLayer::OnUpdate(class Shake::Timestep)","ph":"X","pid":0,"tid":2846169341,"ts":51542316222},{"cat":"function","dur":3,"name":"Gameplay update","ph":"X","pid":0,"tid":2846169341,"ts":51542358398},{"cat":"function","dur":10,"name":"Rendering - Prep","ph":"X","pid":0,"tid":2846169341,"ts":51542358651},{"cat":"function","dur":1611,"name":"Rendering - Draw","ph":"X","pid":0,"tid":2846169341,"ts":51542358829},{"cat":"function","dur":3,"name":"Rendering - Shutdown","ph":"X","pid":0,"tid":2846169341,"ts":51542360676},{"cat":"function","dur":2367,"name":"void __cdecl Shake::EditorLayer::OnUpdate(class Shake::Timestep)","ph":"X","pid":0,"tid":2846169341,"ts":51542358397},{"cat":"function","dur":3,"name":"Gameplay update","ph":"X","pid":0,"tid":2846169341,"ts":51542393973},{"cat":"function","dur":10,"name":"Rendering - Prep","ph":"X","pid":0,"tid":2846169341,"ts":51542394222},{"cat":"function","dur":665,"name":"Rendering - Draw","ph":"X","pid":0,"tid":2846169341,"ts":51542394466},{"cat":"function","dur":3,"name":"Rendering - Shutdown","ph":"X","pid":0,"tid":2846169341,"ts":51542395299},{"cat":"function","dur":1415,"name":"void __cdecl Shake::EditorLayer::OnUpdate(class Shake::Timestep)","ph":"X","pid":0,"tid":2846169341,"ts":51542393972},{"cat":"function","dur":7,"name":"Gameplay update","ph":"X","pid":0,"tid":2846169341,"ts":51542406716},{"cat":"function","dur":10,"name":"Rendering - Prep","ph":"X","pid":0,"tid":2846169341,"ts":51542407010},{"cat":"function","dur":1397,"name":"Rendering - Draw","ph":"X","pid":0,"tid":2846169341,"ts":51542407115},{"cat":"function","dur":2,"name":"Rendering - Shutdown","ph":"X","pid":0,"tid":2846169341,"ts":51542408849},{"cat":"function","dur":2279,"name":"void __cdecl Shake::EditorLayer::OnUpdate(class Shake::Timestep)","ph":"X","pid":0,"tid":2846169341,"ts":51542406715},{"cat":"function","dur":4,"name":"Gameplay update","ph":"X","pid":0,"tid":2846169341,"ts":51542442306},{"cat":"function","dur":19,"name":"Rendering - Prep","ph":"X","pid":0,"tid":2846169341,"ts":51542442715},{"cat":"function","dur":766,"name":"Rendering - Draw","ph":"X","pid":0,"tid":2846169341,"ts":51542442910},{"cat":"function","dur":2,"name":"Rendering - Shutdown","ph":"X","pid":0,"tid":2846169341,"ts":51542443832},{"cat":"function","dur":1611,"name":"void __cdecl Shake::EditorLayer::OnUpdate(class Shake::Timestep)","ph":"X","pid":0,"tid":2846169341,"ts":51542442306},{"cat":"function","dur":3,"name":"Gameplay update","ph":"X","pid":0,"tid":2846169341,"ts":51542453652},{"cat":"function","dur":9,"name":"Rendering - Prep","ph":"X","pid":0,"tid":2846169341,"ts":51542453895},{"cat":"function","dur":637,"name":"Rendering - Draw","ph":"X","pid":0,"tid":2846169341,"ts":51542453993},{"cat":"function","dur":1,"name":"Rendering - Shutdown","ph":"X","pid":0,"tid":2846169341,"ts":51542454751},{"cat":"function","dur":1180,"name":"void __cdecl Shake::EditorLayer::OnUpdate(class Shake::Timestep)","ph":"X","pid":0,"tid":2846169341,"ts":51542453652},{"cat":"function","dur":4,"name":"Gameplay update","ph":"X","pid":0,"tid":2846169341,"ts":51542475097},{"cat":"function","dur":9,"name":"Rendering - Prep","ph":"X","pid":0,"tid":2846169341,"ts":51542475339},{"cat":"function","dur":693,"name":"Rendering - Draw","ph":"X","pid":0,"tid":2846169341,"ts":51542475493},{"cat":"function","dur":1,"name":"Rendering - Shutdown","ph":"X","pid":0,"tid":2846169341,"ts":51542476329},{"cat":"function","dur":1329,"name":"void __cdecl Shake::EditorLayer::OnUpdate(class Shake::Timestep)","ph":"X","pid":0,"tid":2846169341,"ts":51542475097},{"cat":"function","dur":3,"name":"Gameplay update","ph":"X","pid":0,"tid":2846169341,"ts":51542488338},{"cat":"function","dur":9,"name":"Rendering - Prep","ph":"X","pid":0,"tid":2846169341,"ts":51542488744},{"cat":"function","dur":612,"name":"Rendering - Draw","ph":"X","pid":0,"tid":2846169341,"ts":51542488863},{"cat":"function","dur":1,"name":"Rendering - Shutdown","ph":"X","pid":0,"tid":2846169341,"ts":51542489594},{"cat":"function","dur":1337,"name":"void __cdecl Shake::EditorLayer::OnUpdate(class Shake::Timestep)","ph":"X","pid":0,"tid":2846169341,"ts":51542488338},{"cat":"function","dur":5,"name":"Gameplay update","ph":"X","pid":0,"tid":2846169341,"ts":51542502722},{"cat":"function","dur":9,"name":"Rendering - Prep","ph":"X","pid":0,"tid":2846169341,"ts":51542503068},{"cat":"function","dur":444,"name":"Rendering - Draw","ph":"X","pid":0,"tid":2846169341,"ts":51542503173},{"cat":"function","dur":1,"name":"Rendering - Shutdown","ph":"X","pid":0,"tid":2846169341,"ts":51542503712},{"cat":"function","dur":1069,"name":"void __cdecl Shake::EditorLayer::OnUpdate(class Shake::Timestep)","ph":"X","pid":0,"tid":2846169341,"ts":51542502722},{"cat":"function","dur":3,"name":"Gameplay update","ph":"X","pid":0,"tid":2846169341,"ts":51542523029},{"cat":"function","dur":9,"name":"Rendering - Prep","ph":"X","pid":0,"tid":2846169341,"ts":51542523245},{"cat":"function","dur":668,"name":"Rendering - Draw","ph":"X","pid":0,"tid":2846169341,"ts":51542523341},{"cat":"function","dur":1,"name":"Rendering - Shutdown","ph":"X","pid":0,"tid":2846169341,"ts":51542524150},{"cat":"function","dur":1203,"name":"void __cdecl Shake::EditorLayer::OnUpdate(class Shake::Timestep)","ph":"X","pid":0,"tid":2846169341,"ts":51542523029},{"cat":"function","dur":5,"name":"Gameplay update","ph":"X","pid":0,"tid":2846169341,"ts":51542538140},{"cat":"function","dur":12,"name":"Rendering - Prep","ph":"X","pid":0,"tid":2846169341,"ts":51542538594},{"cat":"function","dur":545,"name":"Rendering - Draw","ph":"X","pid":0,"tid":2846169341,"ts":51542538806},{"cat":"function","dur":1,"name":"Rendering - Shutdown","ph":"X","pid":0,"tid":2846169341,"ts":51542539472},{"cat":"function","dur":1427,"name":"void __cdecl Shake::EditorLayer::OnUpdate(class Shake::Timestep)","ph":"X","pid":0,"tid":2846169341,"ts":51542538139},{"cat":"function","dur":3,"name":"Gameplay update","ph":"X","pid":0,"tid":2846169341,"ts":51542557913},{"cat":"function","dur":4,"name":"Rendering - Prep","ph":"X","pid":0,"tid":2846169341,"ts":51542558068},{"cat":"function","dur":539,"name":"Rendering - Draw","ph":"X","pid":0,"tid":2846169341,"ts":51542558187},{"cat":"function","dur":2,"name":"Rendering - Shutdown","ph":"X","pid":0,"tid":2846169341,"ts":51542558877},{"cat":"function","dur":1047,"name":"void __cdecl Shake::EditorLayer::OnUpdate(class Shake::Timestep)","ph":"X","pid":0,"tid":2846169341,"ts":51542557913},{"cat":"function","dur":3,"name":"Gameplay update","ph":"X","pid":0,"tid":2846169341,"ts":51542572296},{"cat":"function","dur":10,"name":"Rendering - Prep","ph":"X","pid":0,"tid":2846169341,"ts":51542572493},{"cat":"function","dur":660,"name":"Rendering - Draw","ph":"X","pid":0,"tid":2846169341,"ts":51542572621},{"cat":"function","dur":3,"name":"Rendering - Shutdown","ph":"X","pid":0,"tid":2846169341,"ts":51542573525},{"cat":"function","dur":1316,"name":"void __cdecl Shake::EditorLayer::OnUpdate(class Shake::Timestep)","ph":"X","pid":0,"tid":2846169341,"ts":51542572296},{"cat":"function","dur":3,"name":"Gameplay update","ph":"X","pid":0,"tid":2846169341,"ts":51542585979},{"cat":"function","dur":6,"name":"Rendering - Prep","ph":"X","pid":0,"tid":2846169341,"ts":51542586141},{"cat":"function","dur":695,"name":"Rendering - Draw","ph":"X","pid":0,"tid":2846169341,"ts":51542586230},{"cat":"function","dur":3,"name":"Rendering - Shutdown","ph":"X","pid":0,"tid":2846169341,"ts":51542587169},{"cat":"function","dur":1336,"name":"void __cdecl Shake::EditorLayer::OnUpdate(class Shake::Timestep)","ph":"X","pid":0,"tid":2846169341,"ts":51542585979},{"cat":"function","dur":3,"name":"Gameplay update","ph":"X","pid":0,"tid":2846169341,"ts":51542606097},{"cat":"function","dur":19,"name":"Rendering - Prep","ph":"X","pid":0,"tid":2846169341,"ts":51542606356},{"cat":"function","dur":840,"name":"Rendering - Draw","ph":"X","pid":0,"tid":2846169341,"ts":51542606471},{"cat":"function","dur":2,"name":"Rendering - Shutdown","ph":"X","pid":0,"tid":2846169341,"ts":51542607488},{"cat":"function","dur":1476,"name":"void __cdecl Shake::EditorLayer::OnUpdate(class Shake::Timestep)","ph":"X","pid":0,"tid":2846169341,"ts":51542606097},{"cat":"function","dur":3,"name":"Gameplay update","ph":"X","pid":0,"tid":2846169341,"ts":51542620201},{"cat":"function","dur":4,"name":"Rendering - Prep","ph":"X","pid":0,"tid":2846169341,"ts":51542620352},{"cat":"function","dur":574,"name":"Rendering - Draw","ph":"X","pid":0,"tid":2846169341,"ts":51542620439},{"cat":"function","dur":2,"name":"Rendering - Shutdown","ph":"X","pid":0,"tid":2846169341,"ts":51542621200},{"cat":"function","dur":1085,"name":"void __cdecl Shake::EditorLayer::OnUpdate(class Shake::Timestep)","ph":"X","pid":0,"tid":2846169341,"ts":51542620201},{"cat":"function","dur":3,"name":"Gameplay update","ph":"X","pid":0,"tid":2846169341,"ts":51542641091},{"cat":"function","dur":5,"name":"Rendering - Prep","ph":"X","pid":0,"tid":2846169341,"ts":51542641250},{"cat":"function","dur":627,"name":"Rendering - Draw","ph":"X","pid":0,"tid":2846169341,"ts":51542641412},{"cat":"function","dur":2,"name":"Rendering - Shutdown","ph":"X","pid":0,"tid":2846169341,"ts":51542642176},{"cat":"function","dur":1182,"name":"void __cdecl Shake::EditorLayer::OnUpdate(class Shake::Timestep)","ph":"X","pid":0,"tid":2846169341,"ts":51542641090},{"cat":"function","dur":2,"name":"Gameplay update","ph":"X","pid":0,"tid":2846169341,"ts":51542654679},{"cat":"function","dur":7,"name":"Rendering - Prep","ph":"X","pid":0,"tid":2846169341,"ts":51542654856},{"cat":"function","dur":516,"name":"Rendering - Draw","ph":"X","pid":0,"tid":2846169341,"ts":51542654989},{"cat":"function","dur":2,"name":"Rendering - Shutdown","ph":"X","pid":0,"tid":2846169341,"ts":51542655625},{"cat":"function","dur":1026,"name":"void __cdecl Shake::EditorLayer::OnUpdate(class Shake::Timestep)","ph":"X","pid":0,"tid":2846169341,"ts":51542654678},{"cat":"function","dur":7,"name":"Gameplay update","ph":"X","pid":0,"tid":2846169341,"ts":51542669512},{"cat":"function","dur":13,"name":"Rendering - Prep","ph":"X","pid":0,"tid":2846169341,"ts":51542669866},{"cat":"function","dur":1128,"name":"Rendering - Draw","ph":"X","pid":0,"tid":2846169341,"ts":51542670046},{"cat":"function","dur":2,"name":"Rendering - Shutdown","ph":"X","pid":0,"tid":2846169341,"ts":51542671286},{"cat":"function","dur":1869,"name":"void __cdecl Shake::EditorLayer::OnUpdate(class Shake::Timestep)","ph":"X","pid":0,"tid":2846169341,"ts":51542669512},{"cat":"function","dur":5,"name":"Gameplay update","ph":"X","pid":0,"tid":2846169341,"ts":51542689538},{"cat":"function","dur":7,"name":"Rendering - Prep","ph":"X","pid":0,"tid":2846169341,"ts":51542689706},{"cat":"function","dur":539,"name":"Rendering - Draw","ph":"X","pid":0,"tid":2846169341,"ts":51542689840},{"cat":"function","dur":3,"name":"Rendering - Shutdown","ph":"X","pid":0,"tid":2846169341,"ts":51542690566},{"cat":"function","dur":1113,"name":"void __cdecl Shake::EditorLayer::OnUpdate(class Shake::Timestep)","ph":"X","pid":0,"tid":2846169341,"ts":51542689538},{"cat":"function","dur":2,"name":"Gameplay update","ph":"X","pid":0,"tid":2846169341,"ts":51542703604},{"cat":"function","dur":9,"name":"Rendering - Prep","ph":"X","pid":0,"tid":2846169341,"ts":51542703804},{"cat":"function","dur":666,"name":"Rendering - Draw","ph":"X","pid":0,"tid":2846169341,"ts":51542703902},{"cat":"function","dur":1,"name":"Rendering - Shutdown","ph":"X","pid":0,"tid":2846169341,"ts":51542704729},{"cat":"function","dur":1218,"name":"void __cdecl Shake::EditorLayer::OnUpdate(class Shake::Timestep)","ph":"X","pid":0,"tid":2846169341,"ts":51542703603},{"cat":"function","dur":3,"name":"Gameplay update","ph":"X","pid":0,"tid":2846169341,"ts":51542724485},{"cat":"function","dur":5,"name":"Rendering - Prep","ph":"X","pid":0,"tid":2846169341,"ts":51542724638},{"cat":"function","dur":413,"name":"Rendering - Draw","ph":"X","pid":0,"tid":2846169341,"ts":51542724741},{"cat":"function","dur":2,"name":"Rendering - Shutdown","ph":"X","pid":0,"tid":2846169341,"ts":51542725332},{"cat":"function","dur":939,"name":"void __cdecl Shake::EditorLayer::OnUpdate(class Shake::Timestep)","ph":"X","pid":0,"tid":2846169341,"ts":51542724485},{"cat":"function","dur":3,"name":"Gameplay update","ph":"X","pid":0,"tid":2846169341,"ts":51542738083},{"cat":"function","dur":5,"name":"Rendering - Prep","ph":"X","pid":0,"tid":2846169341,"ts":51542738232},{"cat":"function","dur":724,"name":"Rendering - Draw","ph":"X","pid":0,"tid":2846169341,"ts":51542738343},{"cat":"function","dur":3,"name":"Rendering - Shutdown","ph":"X","pid":0,"tid":2846169341,"ts":51542739279},{"cat":"function","dur":1282,"name":"void __cdecl Shake::EditorLayer::OnUpdate(class Shake::Timestep)","ph":"X","pid":0,"tid":2846169341,"ts":51542738083},{"cat":"function","dur":3,"name":"Gameplay update","ph":"X","pid":0,"tid":2846169341,"ts":51542752154},{"cat":"function","dur":5,"name":"Rendering - Prep","ph":"X","pid":0,"tid":2846169341,"ts":51542752319},{"cat":"function","dur":756,"name":"Rendering - Draw","ph":"X","pid":0,"tid":2846169341,"ts":51542752411},{"cat":"function","dur":3,"name":"Rendering - Shutdown","ph":"X","pid":0,"tid":2846169341,"ts":51542753448},{"cat":"function","dur":1394,"name":"void __cdecl Shake::EditorLayer::OnUpdate(class Shake::Timestep)","ph":"X","pid":0,"tid":2846169341,"ts":51542752153},{"cat":"function","dur":3,"name":"Gameplay update","ph":"X","pid":0,"tid":2846169341,"ts":51542772669},{"cat":"function","dur":6,"name":"Rendering - Prep","ph":"X","pid":0,"tid":2846169341,"ts":51542772882},{"cat":"function","dur":510,"name":"Rendering - Draw","ph":"X","pid":0,"tid":2846169341,"ts":51542773009},{"cat":"function","dur":1,"name":"Rendering - Shutdown","ph":"X","pid":0,"tid":2846169341,"ts":51542773671},{"cat":"function","dur":1084,"name":"void __cdecl Shake::EditorLayer::OnUpdate(class Shake::Timestep)","ph":"X","pid":0,"tid":2846169341,"ts":51542772669},{"cat":"function","dur":3,"name":"Gameplay update","ph":"X","pid":0,"tid":2846169341,"ts":51542786915},{"cat":"function","dur":5,"name":"Rendering - Prep","ph":"X","pid":0,"tid":2846169341,"ts":51542787065},{"cat":"function","dur":752,"name":"Rendering - Draw","ph":"X","pid":0,"tid":2846169341,"ts":51542787151},{"cat":"function","dur":3,"name":"Rendering - Shutdown","ph":"X","pid":0,"tid":2846169341,"ts":51542788131},{"cat":"function","dur":1302,"name":"void __cdecl Shake::EditorLayer::OnUpdate(class Shake::Timestep)","ph":"X","pid":0,"tid":2846169341,"ts":51542786915},{"cat":"function","dur":4,"name":"Gameplay update","ph":"X","pid":0,"tid":2846169341,"ts":51542807667},{"cat":"function","dur":4,"name":"Rendering - Prep","ph":"X","pid":0,"tid":2846169341,"ts":51542807821},{"cat":"function","dur":455,"name":"Rendering - Draw","ph":"X","pid":0,"tid":2846169341,"ts":51542807931},{"cat":"function","dur":2,"name":"Rendering - Shutdown","ph":"X","pid":0,"tid":2846169341,"ts":51542808514},{"cat":"function","dur":927,"name":"void __cdecl Shake::EditorLayer::OnUpdate(class Shake::Timestep)","ph":"X","pid":0,"tid":2846169341,"ts":51542807667},{"cat":"function","dur":3,"name":"Gameplay update","ph":"X","pid":0,"tid":2846169341,"ts":51542821249},{"cat":"function","dur":9,"name":"Rendering - Prep","ph":"X","pid":0,"tid":2846169341,"ts":51542821484},{"cat":"function","dur":814,"name":"Rendering - Draw","ph":"X","pid":0,"tid":2846169341,"ts":51542821583},{"cat":"function","dur":2,"name":"Rendering - Shutdown","ph":"X","pid":0,"tid":2846169341,"ts":51542822565},{"cat":"function","dur":1398,"name":"void __cdecl Shake::EditorLayer::OnUpdate(class Shake::Timestep)","ph":"X","pid":0,"tid":2846169341,"ts":51542821249},{"cat":"function","dur":3,"name":"Gameplay update","ph":"X","pid":0,"tid":2846169341,"ts":51542835724},{"cat":"function","dur":4,"name":"Rendering - Prep","ph":"X","pid":0,"tid":2846169341,"ts":51542835878},{"cat":"function","dur":506,"name":"Rendering - Draw","ph":"X","pid":0,"tid":2846169341,"ts":51542835964},{"cat":"function","dur":3,"name":"Rendering - Shutdown","ph":"X","pid":0,"tid":2846169341,"ts":51542836821},{"cat":"function","dur":1200,"name":"void __cdecl Shake::EditorLayer::OnUpdate(class Shake::Timestep)","ph":"X","pid":0,"tid":2846169341,"ts":51542835724},{"cat":"function","dur":2,"name":"Gameplay update","ph":"X","pid":0,"tid":2846169341,"ts":51542858533},{"cat":"function","dur":12,"name":"Rendering - Prep","ph":"X","pid":0,"tid":2846169341,"ts":51542858773},{"cat":"function","dur":787,"name":"Rendering - Draw","ph":"X","pid":0,"tid":2846169341,"ts":51542858885},{"cat":"function","dur":2,"name":"Rendering - Shutdown","ph":"X","pid":0,"tid":2846169341,"ts":51542859945},{"cat":"function","dur":1501,"name":"void __cdecl Shake::EditorLayer::OnUpdate(class Shake::Timestep)","ph":"X","pid":0,"tid":2846169341,"ts":51542858532},{"cat":"function","dur":3,"name":"Gameplay update","ph":"X","pid":0,"tid":2846169341,"ts":51542870488},{"cat":"function","dur":7,"name":"Rendering - Prep","ph":"X","pid":0,"tid":2846169341,"ts":51542870659},{"cat":"function","dur":407,"name":"Rendering - Draw","ph":"X","pid":0,"tid":2846169341,"ts":51542870808},{"cat":"function","dur":1,"name":"Rendering - Shutdown","ph":"X","pid":0,"tid":2846169341,"ts":51542871366},{"cat":"function","dur":961,"name":"void __cdecl Shake::EditorLayer::OnUpdate(class Shake::Timestep)","ph":"X","pid":0,"tid":2846169341,"ts":51542870488},{"cat":"function","dur":2,"name":"Gameplay update","ph":"X","pid":0,"tid":2846169341,"ts":51542890842},{"cat":"function","dur":5,"name":"Rendering - Prep","ph":"X","pid":0,"tid":2846169341,"ts":51542890997},{"cat":"function","dur":620,"name":"Rendering - Draw","ph":"X","pid":0,"tid":2846169341,"ts":51542891086},{"cat":"function","dur":3,"name":"Rendering - Shutdown","ph":"X","pid":0,"tid":2846169341,"ts":51542891901},{"cat":"function","dur":1144,"name":"void __cdecl Shake::EditorLayer::OnUpdate(class Shake::Timestep)","ph":"X","pid":0,"tid":2846169341,"ts":51542890841},{"cat":"function","dur":3,"name":"Gameplay update","ph":"X","pid":0,"tid":2846169341,"ts":51542904677},{"cat":"function","dur":5,"name":"Rendering - Prep","ph":"X","pid":0,"tid":2846169341,"ts":51542904826},{"cat":"function","dur":667,"name":"Rendering - Draw","ph":"X","pid":0,"tid":2846169341,"ts":51542904920},{"cat":"function","dur":2,"name":"Rendering - Shutdown","ph":"X","pid":0,"tid":2846169341,"ts":51542905786},{"cat":"function","dur":1195,"name":"void __cdecl Shake::EditorLayer::OnUpdate(class Shake::Timestep)","ph":"X","pid":0,"tid":2846169341,"ts":51542904677},{"cat":"function","dur":3,"name":"Gameplay update","ph":"X","pid":0,"tid":2846169341,"ts":51542918973},{"cat":"function","dur":5,"name":"Rendering - Prep","ph":"X","pid":0,"tid":2846169341,"ts":51542919123},{"cat":"function","dur":582,"name":"Rendering - Draw","ph":"X","pid":0,"tid":2846169341,"ts":51542919210},{"cat":"function","dur":2,"name":"Rendering - Shutdown","ph":"X","pid":0,"tid":2846169341,"ts":51542919993},{"cat":"function","dur":1104,"name":"void __cdecl Shake::EditorLayer::OnUpdate(class Shake::Timestep)","ph":"X","pid":0,"tid":2846169341,"ts":51542918973},{"cat":"function","dur":3,"name":"Gameplay update","ph":"X","pid":0,"tid":2846169341,"ts":51542939459},{"cat":"function","dur":4,"name":"Rendering - Prep","ph":"X","pid":0,"tid":2846169341,"ts":51542939609},{"cat":"function","dur":445,"name":"Rendering - Draw","ph":"X","pid":0,"tid":2846169341,"ts":51542939694},{"cat":"function","dur":3,"name":"Rendering - Shutdown","ph":"X","pid":0,"tid":2846169341,"ts":51542940317},{"cat":"function","dur":946,"name":"void __cdecl Shake::EditorLayer::OnUpdate(class Shake::Timestep)","ph":"X","pid":0,"tid":2846169341,"ts":51542939459},{"cat":"function","dur":2,"name":"Gameplay update","ph":"X","pid":0,"tid":2846169341,"ts":51542953529},{"cat":"function","dur":4,"name":"Rendering - Prep","ph":"X","pid":0,"tid":2846169341,"ts":51542953677},{"cat":"function","dur":623,"name":"Rendering - Draw","ph":"X","pid":0,"tid":2846169341,"ts":51542953768},{"cat":"function","dur":4,"name":"Rendering - Shutdown","ph":"X","pid":0,"tid":2846169341,"ts":51542954766},{"cat":"function","dur":1345,"name":"void __cdecl Shake::EditorLayer::OnUpdate(class Shake::Timestep)","ph":"X","pid":0,"tid":2846169341,"ts":51542953529},{"cat":"function","dur":5,"name":"Gameplay update","ph":"X","pid":0,"tid":2846169341,"ts":51542988124},{"cat":"function","dur":10,"name":"Rendering - Prep","ph":"X","pid":0,"tid":2846169341,"ts":51542988434},{"cat":"function","dur":974,"name":"Rendering - Draw","ph":"X","pid":0,"tid":2846169341,"ts":51542988600},{"cat":"function","dur":1,"name":"Rendering - Shutdown","ph":"X","pid":0,"tid":2846169341,"ts":51542989726},{"cat":"function","dur":1691,"name":"void __cdecl Shake::EditorLayer::OnUpdate(class Shake::Timestep)","ph":"X","pid":0,"tid":2846169341,"ts":51542988123},{"cat":"function","dur":2,"name":"Gameplay update","ph":"X","pid":0,"tid":2846169341,"ts":51543002200},{"cat":"function","dur":6,"name":"Rendering - Prep","ph":"X","pid":0,"tid":2846169341,"ts":51543002349},{"cat":"function","dur":572,"name":"Rendering - Draw","ph":"X","pid":0,"tid":2846169341,"ts":51543002442},{"cat":"function","dur":2,"name":"Rendering - Shutdown","ph":"X","pid":0,"tid":2846169341,"ts":51543003189},{"cat":"function","dur":1082,"name":"void __cdecl Shake::EditorLayer::OnUpdate(class Shake::Timestep)","ph":"X","pid":0,"tid":2846169341,"ts":51543002199},{"cat":"function","dur":2,"name":"Gameplay update","ph":"X","pid":0,"tid":2846169341,"ts":51543022676},{"cat":"function","dur":7,"name":"Rendering - Prep","ph":"X","pid":0,"tid":2846169341,"ts":51543022880},{"cat":"function","dur":627,"name":"Rendering - Draw","ph":"X","pid":0,"tid":2846169341,"ts":51543023031},{"cat":"function","dur":2,"name":"Rendering - Shutdown","ph":"X","pid":0,"tid":2846169341,"ts":51543023800},{"cat":"function","dur":1207,"name":"void __cdecl Shake::EditorLayer::OnUpdate(class Shake::Timestep)","ph":"X","pid":0,"tid":2846169341,"ts":51543022675},{"cat":"function","dur":3,"name":"Gameplay update","ph":"X","pid":0,"tid":2846169341,"ts":51543036733},{"cat":"function","dur":7,"name":"Rendering - Prep","ph":"X","pid":0,"tid":2846169341,"ts":51543036901},{"cat":"function","dur":576,"name":"Rendering - Draw","ph":"X","pid":0,"tid":2846169341,"ts":51543037060},{"cat":"function","dur":3,"name":"Rendering - Shutdown","ph":"X","pid":0,"tid":2846169341,"ts":51543037794},{"cat":"function","dur":1145,"name":"void __cdecl Shake::EditorLayer::OnUpdate(class Shake::Timestep)","ph":"X","pid":0,"tid":2846169341,"ts":51543036733},{"cat":"function","dur":2,"name":"Gameplay update","ph":"X","pid":0,"tid":2846169341,"ts":51543057717},{"cat":"function","dur":7,"name":"Rendering - Prep","ph":"X","pid":0,"tid":2846169341,"ts":51543057876},{"cat":"function","dur":515,"name":"Rendering - Draw","ph":"X","pid":0,"tid":2846169341,"ts":51543058012},{"cat":"function","dur":1,"name":"Rendering - Shutdown","ph":"X","pid":0,"tid":2846169341,"ts":51543058657},{"cat":"function","dur":1020,"name":"void __cdecl Shake::EditorLayer::OnUpdate(class Shake::Timestep)","ph":"X","pid":0,"tid":2846169341,"ts":51543057716},{"cat":"function","dur":3,"name":"Gameplay update","ph":"X","pid":0,"tid":2846169341,"ts":51543071460},{"cat":"function","dur":9,"name":"Rendering - Prep","ph":"X","pid":0,"tid":2846169341,"ts":51543071968},{"cat":"function","dur":508,"name":"Rendering - Draw","ph":"X","pid":0,"tid":2846169341,"ts":51543072084},{"cat":"function","dur":1,"name":"Rendering - Shutdown","ph":"X","pid":0,"tid":2846169341,"ts":51543072693},{"cat":"function","dur":1313,"name":"void __cdecl Shake::EditorLayer::OnUpdate(class Shake::Timestep)","ph":"X","pid":0,"tid":2846169341,"ts":51543071460},{"cat":"function","dur":2,"name":"Gameplay update","ph":"X","pid":0,"tid":2846169341,"ts":51543085488},{"cat":"function","dur":7,"name":"Rendering - Prep","ph":"X","pid":0,"tid":2846169341,"ts":51543085655},{"cat":"function","dur":583,"name":"Rendering - Draw","ph":"X","pid":0,"tid":2846169341,"ts":51543085795},{"cat":"function","dur":1,"name":"Rendering - Shutdown","ph":"X","pid":0,"tid":2846169341,"ts":51543086511},{"cat":"function","dur":1255,"name":"void __cdecl Shake::EditorLayer::OnUpdate(class Shake::Timestep)","ph":"X","pid":0,"tid":2846169341,"ts":51543085487},{"cat":"function","dur":3,"name":"Gameplay update","ph":"X","pid":0,"tid":2846169341,"ts":51543105976},{"cat":"function","dur":8,"name":"Rendering - Prep","ph":"X","pid":0,"tid":2846169341,"ts":51543106153},{"cat":"function","dur":701,"name":"Rendering - Draw","ph":"X","pid":0,"tid":2846169341,"ts":51543106309},{"cat":"function","dur":2,"name":"Rendering - Shutdown","ph":"X","pid":0,"tid":2846169341,"ts":51543107148},{"cat":"function","dur":1283,"name":"void __cdecl Shake::EditorLayer::OnUpdate(class Shake::Timestep)","ph":"X","pid":0,"tid":2846169341,"ts":51543105976},{"cat":"function","dur":2,"name":"Gameplay update","ph":"X","pid":0,"tid":2846169341,"ts":51543120457},{"cat":"function","dur":6,"name":"Rendering - Prep","ph":"X","pid":0,"tid":2846169341,"ts":51543120613},{"cat":"function","dur":433,"name":"Rendering - Draw","ph":"X","pid":0,"tid":2846169341,"ts":51543120750},{"cat":"function","dur":1,"name":"Rendering - Shutdown","ph":"X","pid":0,"tid":2846169341,"ts":51543121301},{"cat":"function","dur":937,"name":"void __cdecl Shake::EditorLayer::OnUpdate(class Shake::Timestep)","ph":"X","pid":0,"tid":2846169341,"ts":51543120457},{"cat":"function","dur":3,"name":"Gameplay update","ph":"X","pid":0,"tid":2846169341,"ts":51543141099},{"cat":"function","dur":7,"name":"Rendering - Prep","ph":"X","pid":0,"tid":2846169341,"ts":51543141257},{"cat":"function","dur":564,"name":"Rendering - Draw","ph":"X","pid":0,"tid":2846169341,"ts":51543141407},{"cat":"function","dur":2,"name":"Rendering - Shutdown","ph":"X","pid":0,"tid":2846169341,"ts":51543142100},{"cat":"function","dur":1084,"name":"void __cdecl Shake::EditorLayer::OnUpdate(class Shake::Timestep)","ph":"X","pid":0,"tid":2846169341,"ts":51543141099},{"cat":"function","dur":4,"name":"Gameplay update","ph":"X","pid":0,"tid":2846169341,"ts":51543154938},{"cat":"function","dur":10,"name":"Rendering - Prep","ph":"X","pid":0,"tid":2846169341,"ts":51543155210},{"cat":"function","dur":1313,"name":"Rendering - Draw","ph":"X","pid":0,"tid":2846169341,"ts":51543155340},{"cat":"function","dur":1,"name":"Rendering - Shutdown","ph":"X","pid":0,"tid":2846169341,"ts":51543156750},{"cat":"function","dur":1890,"name":"void __cdecl Shake::EditorLayer::OnUpdate(class Shake::Timestep)","ph":"X","pid":0,"tid":2846169341,"ts":51543154937},{"cat":"function","dur":5,"name":"Gameplay update","ph":"X","pid":0,"tid":2846169341,"ts":51543169418},{"cat":"function","dur":12,"name":"Rendering - Prep","ph":"X","pid":0,"tid":2846169341,"ts":51543169753},{"cat":"function","dur":1006,"name":"Rendering - Draw","ph":"X","pid":0,"tid":2846169341,"ts":51543169963},{"cat":"function","dur":2,"name":"Rendering - Shutdown","ph":"X","pid":0,"tid":2846169341,"ts":51543171157},{"cat":"function","dur":1885,"name":"void __cdecl Shake::EditorLayer::OnUpdate(class Shake::Timestep)","ph":"X","pid":0,"tid":2846169341,"ts":51543169417},{"cat":"function","dur":5,"name":"Gameplay update","ph":"X","pid":0,"tid":2846169341,"ts":51543189977},{"cat":"function","dur":11,"name":"Rendering - Prep","ph":"X","pid":0,"tid":2846169341,"ts":51543190252},{"cat":"function","dur":1074,"name":"Rendering - Draw","ph":"X","pid":0,"tid":2846169341,"ts":51543190391},{"cat":"function","dur":0,"name":"Rendering - Shutdown","ph":"X","pid":0,"tid":2846169341,"ts":51543191565},{"cat":"function","dur":1666,"name":"void __cdecl Shake::EditorLayer::OnUpdate(class Shake::Timestep)","ph":"X","pid":0,"tid":2846169341,"ts":51543189977},{"cat":"function","dur":5,"name":"Gameplay update","ph":"X","pid":0,"tid":2846169341,"ts":51543204100},{"cat":"function","dur":9,"name":"Rendering - Prep","ph":"X","pid":0,"tid":2846169341,"ts":51543204366},{"cat":"function","dur":1005,"name":"Rendering - Draw","ph":"X","pid":0,"tid":2846169341,"ts":51543204467},{"cat":"function","dur":1,"name":"Rendering - Shutdown","ph":"X","pid":0,"tid":2846169341,"ts":51543205573},{"cat":"function","dur":1559,"name":"void __cdecl Shake::EditorLayer::OnUpdate(class Shake::Timestep)","ph":"X","pid":0,"tid":2846169341,"ts":51543204099},{"cat":"function","dur":2,"name":"Gameplay update","ph":"X","pid":0,"tid":2846169341,"ts":51543237634},{"cat":"function","dur":4,"name":"Rendering - Prep","ph":"X","pid":0,"tid":2846169341,"ts":51543237781},{"cat":"function","dur":380,"name":"Rendering - Draw","ph":"X","pid":0,"tid":2846169341,"ts":51543237867},{"cat":"function","dur":2,"name":"Rendering - Shutdown","ph":"X","pid":0,"tid":2846169341,"ts":51543238424},{"cat":"function","dur":875,"name":"void __cdecl Shake::EditorLayer::OnUpdate(class Shake::Timestep)","ph":"X","pid":0,"tid":2846169341,"ts":51543237633},{"cat":"function","dur":2,"name":"Gameplay update","ph":"X","pid":0,"tid":2846169341,"ts":51543252070},{"cat":"function","dur":4,"name":"Rendering - Prep","ph":"X","pid":0,"tid":2846169341,"ts":51543252221},{"cat":"function","dur":604,"name":"Rendering - Draw","ph":"X","pid":0,"tid":2846169341,"ts":51543252307},{"cat":"function","dur":3,"name":"Rendering - Shutdown","ph":"X","pid":0,"tid":2846169341,"ts":51543253104},{"cat":"function","dur":1118,"name":"void __cdecl Shake::EditorLayer::OnUpdate(class Shake::Timestep)","ph":"X","pid":0,"tid":2846169341,"ts":51543252069},{"cat":"function","dur":2,"name":"Gameplay update","ph":"X","pid":0,"tid":2846169341,"ts":51543272626},{"cat":"function","dur":9,"name":"Rendering - Prep","ph":"X","pid":0,"tid":2846169341,"ts":51543272873},{"cat":"function","dur":538,"name":"Rendering - Draw","ph":"X","pid":0,"tid":2846169341,"ts":51543272979},{"cat":"function","dur":2,"name":"Rendering - Shutdown","ph":"X","pid":0,"tid":2846169341,"ts":51543273648},{"cat":"function","dur":1119,"name":"void __cdecl Shake::EditorLayer::OnUpdate(class Shake::Timestep)","ph":"X","pid":0,"tid":2846169341,"ts":51543272625},{"cat":"function","dur":3,"name":"Gameplay update","ph":"X","pid":0,"tid":2846169341,"ts":51543286833},{"cat":"function","dur":5,"name":"Rendering - Prep","ph":"X","pid":0,"tid":2846169341,"ts":51543286989},{"cat":"function","dur":742,"name":"Rendering - Draw","ph":"X","pid":0,"tid":2846169341,"ts":51543287078},{"cat":"function","dur":3,"name":"Rendering - Shutdown","ph":"X","pid":0,"tid":2846169341,"ts":51543288032},{"cat":"function","dur":1286,"name":"void __cdecl Shake::EditorLayer::OnUpdate(class Shake::Timestep)","ph":"X","pid":0,"tid":2846169341,"ts":51543286833},{"cat":"function","dur":2,"name":"Gameplay update","ph":"X","pid":0,"tid":2846169341,"ts":51543308005},{"cat":"function","dur":6,"name":"Rendering - Prep","ph":"X","pid":0,"tid":2846169341,"ts":51543308168},{"cat":"function","dur":623,"name":"Rendering - Draw","ph":"X","pid":0,"tid":2846169341,"ts":51543308340},{"cat":"function","dur":2,"name":"Rendering - Shutdown","ph":"X","pid":0,"tid":2846169341,"ts":51543309100},{"cat":"function","dur":1180,"name":"void __cdecl Shake::EditorLayer::OnUpdate(class Shake::Timestep)","ph":"X","pid":0,"tid":2846169341,"ts":51543308004},{"cat":"function","dur":3,"name":"Gameplay update","ph":"X","pid":0,"tid":2846169341,"ts":51543321469},{"cat":"function","dur":9,"name":"Rendering - Prep","ph":"X","pid":0,"tid":2846169341,"ts":51543321672},{"cat":"function","dur":1033,"name":"Rendering - Draw","ph":"X","pid":0,"tid":2846169341,"ts":51543321774},{"cat":"function","dur":1,"name":"Rendering - Shutdown","ph":"X","pid":0,"tid":2846169341,"ts":51543322949},{"cat":"function","dur":1558,"name":"void __cdecl Shake::EditorLayer::OnUpdate(class Shake::Timestep)","ph":"X","pid":0,"tid":2846169341,"ts":51543321469},{"cat":"function","dur":3,"name":"Gameplay update","ph":"X","pid":0,"tid":2846169341,"ts":51543335899},{"cat":"function","dur":11,"name":"Rendering - Prep","ph":"X","pid":0,"tid":2846169341,"ts":51543336226},{"cat":"function","dur":457,"name":"Rendering - Draw","ph":"X","pid":0,"tid":2846169341,"ts":51543336455},{"cat":"function","dur":2,"name":"Rendering - Shutdown","ph":"X","pid":0,"tid":2846169341,"ts":51543337017},{"cat":"function","dur":1202,"name":"void __cdecl Shake::EditorLayer::OnUpdate(class Shake::Timestep)","ph":"X","pid":0,"tid":2846169341,"ts":51543335898},{"cat":"function","dur":2,"name":"Gameplay update","ph":"X","pid":0,"tid":2846169341,"ts":51543356303},{"cat":"function","dur":9,"name":"Rendering - Prep","ph":"X","pid":0,"tid":2846169341,"ts":51543356498},{"cat":"function","dur":521,"name":"Rendering - Draw","ph":"X","pid":0,"tid":2846169341,"ts":51543356656},{"cat":"function","dur":2,"name":"Rendering - Shutdown","ph":"X","pid":0,"tid":2846169341,"ts":51543357296},{"cat":"function","dur":1077,"name":"void __cdecl Shake::EditorLayer::OnUpdate(class Shake::Timestep)","ph":"X","pid":0,"tid":2846169341,"ts":51543356302},{"cat":"function","dur":3,"name":"Gameplay update","ph":"X","pid":0,"tid":2846169341,"ts":51543370764},{"cat":"function","dur":9,"name":"Rendering - Prep","ph":"X","pid":0,"tid":2846169341,"ts":51543371133},{"cat":"function","dur":459,"name":"Rendering - Draw","ph":"X","pid":0,"tid":2846169341,"ts":51543371252},{"cat":"function","dur":1,"name":"Rendering - Shutdown","ph":"X","pid":0,"tid":2846169341,"ts":51543371824},{"cat":"function","dur":1141,"name":"void __cdecl Shake::EditorLayer::OnUpdate(class Shake::Timestep)","ph":"X","pid":0,"tid":2846169341,"ts":51543370764},{"cat":"function","dur":2,"name":"Gameplay update","ph":"X","pid":0,"tid":2846169341,"ts":51543392011},{"cat":"function","dur":5,"name":"Rendering - Prep","ph":"X","pid":0,"tid":2846169341,"ts":51543392175},{"cat":"function","dur":669,"name":"Rendering - Draw","ph":"X","pid":0,"tid":2846169341,"ts":51543392262},{"cat":"function","dur":3,"name":"Rendering - Shutdown","ph":"X","pid":0,"tid":2846169341,"ts":51543393165},{"cat":"function","dur":1248,"name":"void __cdecl Shake::EditorLayer::OnUpdate(class Shake::Timestep)","ph":"X","pid":0,"tid":2846169341,"ts":51543392010},{"cat":"function","dur":3,"name":"Gameplay update","ph":"X","pid":0,"tid":2846169341,"ts":51543405064},{"cat":"function","dur":7,"name":"Rendering - Prep","ph":"X","pid":0,"tid":2846169341,"ts":51543405226},{"cat":"function","dur":554,"name":"Rendering - Draw","ph":"X","pid":0,"tid":2846169341,"ts":51543405368},{"cat":"function","dur":3,"name":"Rendering - Shutdown","ph":"X","pid":0,"tid":2846169341,"ts":51543406085},{"cat":"function","dur":1106,"name":"void __cdecl Shake::EditorLayer::OnUpdate(class Shake::Timestep)","ph":"X","pid":0,"tid":2846169341,"ts":51543405064},{"cat":"function","dur":3,"name":"Gameplay update","ph":"X","pid":0,"tid":2846169341,"ts":51543419358},{"cat":"function","dur":5,"name":"Rendering - Prep","ph":"X","pid":0,"tid":2846169341,"ts":51543419515},{"cat":"function","dur":532,"name":"Rendering - Draw","ph":"X","pid":0,"tid":2846169341,"ts":51543419603},{"cat":"function","dur":2,"name":"Rendering - Shutdown","ph":"X","pid":0,"tid":2846169341,"ts":51543420342},{"cat":"function","dur":1078,"name":"void __cdecl Shake::EditorLayer::OnUpdate(class Shake::Timestep)","ph":"X","pid":0,"tid":2846169341,"ts":51543419358},{"cat":"function","dur":3,"name":"Gameplay update","ph":"X","pid":0,"tid":2846169341,"ts":51543439644},{"cat":"function","dur":5,"name":"Rendering - Prep","ph":"X","pid":0,"tid":2846169341,"ts":51543439802},{"cat":"function","dur":653,"name":"Rendering - Draw","ph":"X","pid":0,"tid":2846169341,"ts":51543439889},{"cat":"function","dur":3,"name":"Rendering - Shutdown","ph":"X","pid":0,"tid":2846169341,"ts":51543440758},{"cat":"function","dur":1199,"name":"void __cdecl Shake::EditorLayer::OnUpdate(class Shake::Timestep)","ph":"X","pid":0,"tid":2846169341,"ts":51543439644},{"cat":"function","dur":3,"name":"Gameplay update","ph":"X","pid":0,"tid":2846169341,"ts":51543453468},{"cat":"function","dur":4,"name":"Rendering - Prep","ph":"X","pid":0,"tid":2846169341,"ts":51543453625},{"cat":"function","dur":446,"name":"Rendering - Draw","ph":"X","pid":0,"tid":2846169341,"ts":51543453710},{"cat":"function","dur":2,"name":"Rendering - Shutdown","ph":"X","pid":0,"tid":2846169341,"ts":51543454318},{"cat":"function","dur":938,"name":"void __cdecl Shake::EditorLayer::OnUpdate(class Shake::Timestep)","ph":"X","pid":0,"tid":2846169341,"ts":51543453468}]}